pyMSDtorch
