Metadata-Version: 2.1
Name: pyMSDtorch
Version: 0.1.6
Summary: Python Boilerplate contains all the boilerplate you need to create a Python package.
Home-page: https://bitbucket.org/berkeleylab/pymsdtorch/
Author: Petrus H. Zwart, Eric J. Roberts
Author-email: PHZwart@lbl.gov, EJroberts@lbl.gov
License: BSD License
Keywords: pyMSDtorch
Classifier: Development Status :: 2 - Pre-Alpha
Classifier: Intended Audience :: Developers
Classifier: License :: OSI Approved :: BSD License
Classifier: Natural Language :: English
Classifier: Programming Language :: Python :: 3
Classifier: Programming Language :: Python :: 3.5
Classifier: Programming Language :: Python :: 3.6
Classifier: Programming Language :: Python :: 3.7
Classifier: Programming Language :: Python :: 3.8
Requires-Python: >=3.8
License-File: LICENSE
License-File: AUTHORS.rst
